geodataExtent/__init__.py
geodataExtent/extractGeoDataFromFolder.py
geodataExtent/getBoundingBox.py
geodataExtent/getPolygon.py
geodataExtent/getTimeExtent.py
geodataExtent/masterExtract.py
geodataExtent/sendToPyCSW.py
geodataExtent-0.2.8.dist-info/LICENCE
geodataExtent-0.2.8.dist-info/METADATA
geodataExtent-0.2.8.dist-info/WHEEL
geodataExtent-0.2.8.dist-info/entry_points.txt
geodataExtent-0.2.8.dist-info/top_level.txt
geodataExtent-0.2.8.dist-info/RECORD
